oqs/__init__.py
oqs/oqs.py
oqs/rand.py
liboqs_pwr-0.12.1.dist-info/LICENSE.txt
liboqs_pwr-0.12.1.dist-info/METADATA
liboqs_pwr-0.12.1.dist-info/WHEEL
liboqs_pwr-0.12.1.dist-info/RECORD
