Metadata-Version: 2.1
Name: liboqs-pwr
Version: 0.12.1
Summary: Python bindings for liboqs, providing post-quantum public key cryptography algorithms
Home-page: https://github.com/keep-pwr-strong/liboqs-pwr
License: MIT
Keywords: liboqs,post-quantum,cryptography,oqs,security
Author: Open Quantum Safe project
Author-email: contact@openquantumsafe.org
Requires-Python: >=3.9
Classifier: License :: OSI Approved :: MIT License
Classifier: Programming Language :: Python :: 3
Classifier: Programming Language :: Python :: 3.9
Classifier: Programming Language :: Python :: 3.10
Classifier: Programming Language :: Python :: 3.11
Classifier: Programming Language :: Python :: 3.12
Requires-Dist: cryptography (>=44.0.2,<45.0.0)
Requires-Dist: mypy (>=1.14.1,<2.0.0)
Requires-Dist: requests (>=2.32.3,<3.0.0)
Project-URL: Documentation, https://docs.openquantumsafe.org/
Project-URL: Repository, https://github.com/keep-pwr-strong/liboqs-pwr
